deltalake_tools/__init__.py
deltalake_tools/__version__.py
deltalake_tools/cli/cli.py
deltalake_tools/core/convert.py
deltalake_tools/core/core.py
deltalake_tools/helpers/__init__.py
deltalake_tools/helpers/helpers.py
deltalake_tools/models/models.py
deltalake_tools/result/__init__.py
deltalake_tools-0.2.0.dist-info/METADATA
deltalake_tools-0.2.0.dist-info/WHEEL
deltalake_tools-0.2.0.dist-info/entry_points.txt
deltalake_tools-0.2.0.dist-info/licenses/LICENSE
deltalake_tools-0.2.0.dist-info/RECORD
