Metadata-Version: 2.3
Name: deltalake-tools
Version: 0.2.0
Summary: A set of easy to use convenient tools for deltalake tables. 
Author-email: jeroenflvr <jeroen@flexworks.eu>
License: Apache-2.0
Classifier: License :: OSI Approved :: Apache Software License
Classifier: Programming Language :: Python :: 3.10
Classifier: Programming Language :: Python :: 3.11
Classifier: Programming Language :: Python :: 3.12
Requires-Python: >=3.10
Requires-Dist: boto3>=1.35.71
Requires-Dist: click>=8.1.7
Requires-Dist: deltalake>=0.21.0
Requires-Dist: pydantic>=2.9.2
